project_summary/__init__.py
project_summary/cli.py
project_summary/config.py
project_summary/core.py
project_summary-0.2.1.dist-info/METADATA
project_summary-0.2.1.dist-info/WHEEL
project_summary-0.2.1.dist-info/entry_points.txt
project_summary-0.2.1.dist-info/licenses/LICENSE
project_summary-0.2.1.dist-info/RECORD
