Metadata-Version: 2.4
Name: project-summary
Version: 0.2.1
Summary: Tool for generating project structure and content summaries
Project-URL: Homepage, https://github.com/fedorello/project-summary
Project-URL: Repository, https://github.com/fedorello/project-summary.git
Project-URL: Issues, https://github.com/fedorello/project-summary/issues
Project-URL: Changelog, https://github.com/fedorello/project-summary/blob/main/CHANGELOG.md
Author-email: Fedorello <fedorstartup@gmail.com>
License: MIT License
License-File: LICENSE
Keywords: analysis,documentation,project,structure,summary
Classifier: Development Status :: 4 - Beta
Classifier: Environment :: Console
Classifier: Intended Audience :: Developers
Classifier: License :: OSI Approved :: MIT License
Classifier: Operating System :: OS Independent
Classifier: Programming Language :: Python :: 3
Classifier: Programming Language :: Python :: 3.6
Classifier: Programming Language :: Python :: 3.7
Classifier: Programming Language :: Python :: 3.8
Classifier: Programming Language :: Python :: 3.9
Classifier: Programming Language :: Python :: 3.10
Classifier: Programming Language :: Python :: 3.11
Classifier: Topic :: Software Development :: Documentation
Classifier: Topic :: Software Development :: Libraries :: Python Modules
Requires-Dist: pathlib>=1.0
Requires-Dist: pyyaml>=6.0
